[
  {
    "id": "prod-1772443321242",
    "slug": "new-product-1772443321242",
    "title": "Новый товар",
    "category": "Стулья",
    "priceFrom": 0,
    "availability": "made-to-order",
    "badges": [],
    "tags": [],
    "upholstery": "Микровелюр",
    "legsMaterial": "Березовая фанера",
    "legsColor": "Орех",
    "imagePath": "",
    "shortDescription": ""
  },
  {
    "id": "prod-1772443321110",
    "slug": "new-product-1772443321110",
    "title": "Новый товар",
    "category": "Стулья",
    "priceFrom": 0,
    "availability": "made-to-order",
    "badges": [],
    "tags": [],
    "upholstery": "Микровелюр",
    "legsMaterial": "Березовая фанера",
    "legsColor": "Орех",
    "imagePath": "",
    "shortDescription": ""
  },
  {
    "id": "prod-1772443320971",
    "slug": "new-product-1772443320971",
    "title": "Новый товар",
    "category": "Стулья",
    "priceFrom": 0,
    "availability": "made-to-order",
    "badges": [],
    "tags": [],
    "upholstery": "Микровелюр",
    "legsMaterial": "Березовая фанера",
    "legsColor": "Орех",
    "imagePath": "",
    "shortDescription": ""
  },
  {
    "id": "prod-1772443320820",
    "slug": "new-product-1772443320820",
    "title": "Новый товар",
    "category": "Стулья",
    "priceFrom": 0,
    "availability": "made-to-order",
    "badges": [],
    "tags": [],
    "upholstery": "Микровелюр",
    "legsMaterial": "Березовая фанера",
    "legsColor": "Орех",
    "imagePath": "",
    "shortDescription": ""
  },
  {
    "id": "prod-1772443320663",
    "slug": "new-product-1772443320663",
    "title": "Новый товар",
    "category": "Стулья",
    "priceFrom": 0,
    "availability": "made-to-order",
    "badges": [],
    "tags": [],
    "upholstery": "Микровелюр",
    "legsMaterial": "Березовая фанера",
    "legsColor": "Орех",
    "imagePath": "",
    "shortDescription": ""
  },
  {
    "id": "prod-1772443320514",
    "slug": "new-product-1772443320514",
    "title": "Новый товар",
    "category": "Стулья",
    "priceFrom": 0,
    "availability": "made-to-order",
    "badges": [],
    "tags": [],
    "upholstery": "Микровелюр",
    "legsMaterial": "Березовая фанера",
    "legsColor": "Орех",
    "imagePath": "",
    "shortDescription": ""
  },
  {
    "id": "prod-1772443320391",
    "slug": "new-product-1772443320391",
    "title": "Новый товар",
    "category": "Стулья",
    "priceFrom": 0,
    "availability": "made-to-order",
    "badges": [],
    "tags": [],
    "upholstery": "Микровелюр",
    "legsMaterial": "Березовая фанера",
    "legsColor": "Орех",
    "imagePath": "",
    "shortDescription": ""
  },
  {
    "id": "prod-1772443320245",
    "slug": "new-product-1772443320245",
    "title": "Новый товар",
    "category": "Стулья",
    "priceFrom": 0,
    "availability": "made-to-order",
    "badges": [],
    "tags": [],
    "upholstery": "Микровелюр",
    "legsMaterial": "Березовая фанера",
    "legsColor": "Орех",
    "imagePath": "",
    "shortDescription": ""
  },
  {
    "id": "prod-1772443320106",
    "slug": "new-product-1772443320106",
    "title": "Новый товар",
    "category": "Стулья",
    "priceFrom": 0,
    "availability": "made-to-order",
    "badges": [],
    "tags": [],
    "upholstery": "Микровелюр",
    "legsMaterial": "Березовая фанера",
    "legsColor": "Орех",
    "imagePath": "",
    "shortDescription": ""
  },
  {
    "id": "prod-1772443319386",
    "slug": "new-product-1772443319386",
    "title": "Новый товар",
    "category": "Стулья",
    "priceFrom": 0,
    "availability": "made-to-order",
    "badges": [],
    "tags": [],
    "upholstery": "Микровелюр",
    "legsMaterial": "Березовая фанера",
    "legsColor": "Орех",
    "imagePath": "",
    "shortDescription": ""
  },
  {
    "id": "prod-1772443319253",
    "slug": "new-product-1772443319253",
    "title": "Новый товар",
    "category": "Стулья",
    "priceFrom": 0,
    "availability": "made-to-order",
    "badges": [],
    "tags": [],
    "upholstery": "Микровелюр",
    "legsMaterial": "Березовая фанера",
    "legsColor": "Орех",
    "imagePath": "",
    "shortDescription": ""
  },
  {
    "id": "prod-1772443319119",
    "slug": "new-product-1772443319119",
    "title": "Новый товар",
    "category": "Стулья",
    "priceFrom": 0,
    "availability": "made-to-order",
    "badges": [],
    "tags": [],
    "upholstery": "Микровелюр",
    "legsMaterial": "Березовая фанера",
    "legsColor": "Орех",
    "imagePath": "",
    "shortDescription": ""
  },
  {
    "id": "prod-1772443318970",
    "slug": "new-product-1772443318970",
    "title": "Новый товар",
    "category": "Стулья",
    "priceFrom": 0,
    "availability": "made-to-order",
    "badges": [],
    "tags": [],
    "upholstery": "Микровелюр",
    "legsMaterial": "Березовая фанера",
    "legsColor": "Орех",
    "imagePath": "",
    "shortDescription": ""
  },
  {
    "id": "prod-1772443318848",
    "slug": "new-product-1772443318848",
    "title": "Новый товар",
    "category": "Стулья",
    "priceFrom": 0,
    "availability": "made-to-order",
    "badges": [],
    "tags": [],
    "upholstery": "Микровелюр",
    "legsMaterial": "Березовая фанера",
    "legsColor": "Орех",
    "imagePath": "",
    "shortDescription": ""
  },
  {
    "id": "prod-1772443318702",
    "slug": "new-product-1772443318702",
    "title": "Новый товар",
    "category": "Стулья",
    "priceFrom": 0,
    "availability": "made-to-order",
    "badges": [],
    "tags": [],
    "upholstery": "Микровелюр",
    "legsMaterial": "Березовая фанера",
    "legsColor": "Орех",
    "imagePath": "",
    "shortDescription": ""
  },
  {
    "id": "prod-1772443318579",
    "slug": "new-product-1772443318579",
    "title": "Новый товар",
    "category": "Стулья",
    "priceFrom": 0,
    "availability": "made-to-order",
    "badges": [],
    "tags": [],
    "upholstery": "Микровелюр",
    "legsMaterial": "Березовая фанера",
    "legsColor": "Орех",
    "imagePath": "",
    "shortDescription": ""
  },
  {
    "id": "prod-1772443318437",
    "slug": "new-product-1772443318437",
    "title": "Новый товар",
    "category": "Стулья",
    "priceFrom": 0,
    "availability": "made-to-order",
    "badges": [],
    "tags": [],
    "upholstery": "Микровелюр",
    "legsMaterial": "Березовая фанера",
    "legsColor": "Орех",
    "imagePath": "",
    "shortDescription": ""
  },
  {
    "id": "prod-1772443318302",
    "slug": "new-product-1772443318302",
    "title": "Новый товар",
    "category": "Стулья",
    "priceFrom": 0,
    "availability": "made-to-order",
    "badges": [],
    "tags": [],
    "upholstery": "Микровелюр",
    "legsMaterial": "Березовая фанера",
    "legsColor": "Орех",
    "imagePath": "",
    "shortDescription": ""
  },
  {
    "id": "prod-1772443318177",
    "slug": "new-product-1772443318177",
    "title": "Новый товар",
    "category": "Стулья",
    "priceFrom": 0,
    "availability": "made-to-order",
    "badges": [],
    "tags": [],
    "upholstery": "Микровелюр",
    "legsMaterial": "Березовая фанера",
    "legsColor": "Орех",
    "imagePath": "",
    "shortDescription": ""
  },
  {
    "id": "prod-1772443318050",
    "slug": "new-product-1772443318050",
    "title": "Новый товар",
    "category": "Стулья",
    "priceFrom": 0,
    "availability": "made-to-order",
    "badges": [],
    "tags": [],
    "upholstery": "Микровелюр",
    "legsMaterial": "Березовая фанера",
    "legsColor": "Орех",
    "imagePath": "",
    "shortDescription": ""
  },
  {
    "id": "prod-1772443317926",
    "slug": "new-product-1772443317926",
    "title": "Новый товар",
    "category": "Стулья",
    "priceFrom": 0,
    "availability": "made-to-order",
    "badges": [],
    "tags": [],
    "upholstery": "Микровелюр",
    "legsMaterial": "Березовая фанера",
    "legsColor": "Орех",
    "imagePath": "",
    "shortDescription": ""
  },
  {
    "id": "prod-1772443317814",
    "slug": "new-product-1772443317814",
    "title": "Новый товар",
    "category": "Стулья",
    "priceFrom": 0,
    "availability": "made-to-order",
    "badges": [],
    "tags": [],
    "upholstery": "Микровелюр",
    "legsMaterial": "Березовая фанера",
    "legsColor": "Орех",
    "imagePath": "",
    "shortDescription": ""
  },
  {
    "id": "prod-1772443317674",
    "slug": "new-product-1772443317674",
    "title": "Новый товар",
    "category": "Стулья",
    "priceFrom": 0,
    "availability": "made-to-order",
    "badges": [],
    "tags": [],
    "upholstery": "Микровелюр",
    "legsMaterial": "Березовая фанера",
    "legsColor": "Орех",
    "imagePath": "",
    "shortDescription": ""
  },
  {
    "id": "prod-1772443317555",
    "slug": "new-product-1772443317555",
    "title": "Новый товар",
    "category": "Стулья",
    "priceFrom": 0,
    "availability": "made-to-order",
    "badges": [],
    "tags": [],
    "upholstery": "Микровелюр",
    "legsMaterial": "Березовая фанера",
    "legsColor": "Орех",
    "imagePath": "",
    "shortDescription": ""
  },
  {
    "id": "prod-1772443317414",
    "slug": "new-product-1772443317414",
    "title": "Новый товар",
    "category": "Стулья",
    "priceFrom": 0,
    "availability": "made-to-order",
    "badges": [],
    "tags": [],
    "upholstery": "Микровелюр",
    "legsMaterial": "Березовая фанера",
    "legsColor": "Орех",
    "imagePath": "",
    "shortDescription": ""
  },
  {
    "id": "prod-1772443317245",
    "slug": "new-product-1772443317245",
    "title": "Новый товар",
    "category": "Стулья",
    "priceFrom": 0,
    "availability": "made-to-order",
    "badges": [],
    "tags": [],
    "upholstery": "Микровелюр",
    "legsMaterial": "Березовая фанера",
    "legsColor": "Орех",
    "imagePath": "",
    "shortDescription": ""
  },
  {
    "id": "prod-1772443317093",
    "slug": "new-product-1772443317093",
    "title": "Новый товар",
    "category": "Стулья",
    "priceFrom": 0,
    "availability": "made-to-order",
    "badges": [],
    "tags": [],
    "upholstery": "Микровелюр",
    "legsMaterial": "Березовая фанера",
    "legsColor": "Орех",
    "imagePath": "",
    "shortDescription": ""
  },
  {
    "id": "prod-1772443316935",
    "slug": "new-product-1772443316935",
    "title": "Новый товар",
    "category": "Стулья",
    "priceFrom": 0,
    "availability": "made-to-order",
    "badges": [],
    "tags": [],
    "upholstery": "Микровелюр",
    "legsMaterial": "Березовая фанера",
    "legsColor": "Орех",
    "imagePath": "",
    "shortDescription": ""
  },
  {
    "id": "prod-1772443316542",
    "slug": "new-product-1772443316542",
    "title": "Новый товар",
    "category": "Стулья",
    "priceFrom": 0,
    "availability": "made-to-order",
    "badges": [],
    "tags": [],
    "upholstery": "Микровелюр",
    "legsMaterial": "Березовая фанера",
    "legsColor": "Орех",
    "imagePath": "",
    "shortDescription": ""
  },
  {
    "id": "prod-1772439415201",
    "slug": "new-product-1772439415201",
    "title": "Новый товар",
    "category": "Стулья",
    "priceFrom": 100,
    "availability": "made-to-order",
    "badges": [],
    "tags": [],
    "upholstery": "Экокожа",
    "legsMaterial": "Массив дуба",
    "legsColor": "Натуральный",
    "imagePath": "/generated/1772439418677_img_1849.webp",
    "shortDescription": ""
  },
  {
    "id": "prod-1772396938703",
    "slug": "new-product-1772396938703",
    "title": "AURORA",
    "category": "Табуретки",
    "priceFrom": 5000,
    "availability": "made-to-order",
    "badges": [],
    "tags": [],
    "upholstery": "Микровелюр",
    "legsMaterial": "Березовая фанера",
    "legsColor": "Орех",
    "imagePath": "/generated/1772396944943_img_1847.webp",
    "shortDescription": "",
    "galleryImages": [
      "/generated/1772397506841_img_1833.webp",
      "/generated/1772397509045_img_1842.webp",
      "/generated/1772397511431_img_1838.webp",
      "/generated/1772397514346_img_1847.webp"
    ]
  }
]